{
  "annotations": {
    "changelogDate": "20231217231954"
  },
  "dto": "mapstruct",
  "entityTableName": "cliente_accion",
  "fields": [
    {
      "fieldName": "cliente",
      "fieldType": "Integer",
      "fieldValidateRules": ["required"]
    },
    {
      "fieldName": "accionId",
      "fieldType": "Integer",
      "fieldValidateRules": ["required"]
    },
    {
      "fieldName": "accion",
      "fieldType": "String"
    },
    {
      "fieldName": "cantidadActual",
      "fieldType": "Integer"
    },
    {
      "fieldName": "observaciones",
      "fieldType": "String"
    }
  ],
  "jpaMetamodelFiltering": false,
  "name": "ClienteAccion",
  "pagination": "no",
  "readOnly": false,
  "relationships": [],
  "searchEngine": "no",
  "service": "serviceImpl"
}
